{
  "$schema": "https://json-schema.org/draft-07/schema",
  "type": "object",
  "properties": {
    "SluggiesModel": {
      "type": "object",
      "description": "MSS Model Folder",
      "properties": {
        "ChunkNumber": {
          "type": "number",
          "description": "Folder number the exported model is found in"
        },
        "ModelOffset": {
          "type": "string",
          "description": "Starting offset of model data in dt_na.dat (hex)"
        },
        "ModelLength": {
          "type": "number",
          "description": "Full length of model data (in bytes) from offset adress to end of model data"
        },
        "Submeshes": {
          "type": "array",
          "description": "There can be multiple separate submeshes in one model.",
          "items": {
            "type": "object",
            "properties": {
              "SubmeshOffset": {
                "type": "string",
                "description": "Starting offset of this submesh in dt_na.dat (hex)"
              },
              "SubmeshLength": {
                "type": "number",
                "description": "Length of this submesh data in bytes"
              },
              "FacesCount": {
                "type": "number",
                "description": "Number of triangle faces"
              },
              "FacesData": {
                "type": "string",
                "description": "Base64-encoded face index buffer. Packed as big-endian uint16 triplets: [i0, i1, i2, i0, i1, i2, ...]"
              },
              "VertexBuffer": {
                "type": "object",
                "description": "XYZ position vertex buffer for this submesh",
                "properties": {
                  "VertexBufferOffset": {
                    "type": "string",
                    "description": "Starting offset of the vertex position buffer in dt_na.dat (hex)"
                  },
                  "VertexBufferLength": {
                    "type": "number",
                    "description": "Length of the vertex position buffer in bytes"
                  },
                  "VertexBufferCompCount": {
                    "type": "number",
                    "description": "Number of components per vertex entry. 3 = XYZ only, 6 = XYZ+NormalXYZ interleaved (skinned meshes)"
                  },
                  "VertexBufferQuantizeInfo": {
                    "type": "number",
                    "description": "Quantization byte. High nibble = data format (0/3=s16, 4=float), low nibble = right-shift divisor exponent"
                  },
                  "VertexBufferData": {
                    "type": "string",
                    "description": "Base64-encoded raw vertex position buffer bytes"
                  }
                },
                "required": ["VertexBufferOffset", "VertexBufferLength", "VertexBufferCompCount", "VertexBufferQuantizeInfo", "VertexBufferData"]
              },
              "UVMap": {
                "type": "object",
                "description": "UV mapping data for this submesh",
                "properties": {
                  "UVMapOffset": {
                    "type": "string",
                    "description": "Starting offset of the UV map buffer in dt_na.dat (hex)"
                  },
                  "UVMapLength": {
                    "type": "number",
                    "description": "Length of the UV map buffer in bytes"
                  }
                },
                "required": ["UVMapOffset", "UVMapLength"]
              }
            },
            "required": ["SubmeshOffset", "SubmeshLength", "VertexBuffer", "UVMap"]
          }
        }
      },
      "required": [
        "ChunkNumber",
        "ModelOffset",
        "ModelLength"
      ]
    }
  },
  "required": [
    "SluggiesModel"
  ]
}